odoo/addons/account_statement_import_sftp/README.rst
odoo/addons/account_statement_import_sftp/__init__.py
odoo/addons/account_statement_import_sftp/__manifest__.py
odoo/addons/account_statement_import_sftp/components/__init__.py
odoo/addons/account_statement_import_sftp/components/account_statement_import_process.py
odoo/addons/account_statement_import_sftp/data/edi_data.xml
odoo/addons/account_statement_import_sftp/i18n/account_statement_import_sftp.pot
odoo/addons/account_statement_import_sftp/i18n/it.po
odoo/addons/account_statement_import_sftp/readme/CONFIGURE.rst
odoo/addons/account_statement_import_sftp/readme/CONTRIBUTORS.rst
odoo/addons/account_statement_import_sftp/readme/DESCRIPTION.rst
odoo/addons/account_statement_import_sftp/readme/HISTORY.rst
odoo/addons/account_statement_import_sftp/readme/USAGE.rst
odoo/addons/account_statement_import_sftp/static/description/icon.png
odoo/addons/account_statement_import_sftp/static/description/index.html
odoo/addons/account_statement_import_sftp/test_files/camt053
odoo/addons/account_statement_import_sftp/tests/__init__.py
odoo/addons/account_statement_import_sftp/tests/test_account_statement_import_process.py
odoo14_addon_account_statement_import_sftp-14.0.1.0.1.dev6.dist-info/METADATA
odoo14_addon_account_statement_import_sftp-14.0.1.0.1.dev6.dist-info/WHEEL
odoo14_addon_account_statement_import_sftp-14.0.1.0.1.dev6.dist-info/top_level.txt
odoo14_addon_account_statement_import_sftp-14.0.1.0.1.dev6.dist-info/RECORD
