Metadata-Version: 2.1
Name: odoo14-addon-account_statement_import_sftp
Version: 14.0.1.0.1.dev6
Summary: Import bank statement from an SFTP server
Home-page: https://github.com/OCA/bank-statement-import
Author: Odoo Community Association (OCA), Compassion CH
Author-email: support@odoo-community.org
License: AGPL-3
Classifier: Programming Language :: Python
Classifier: Framework :: Odoo
Classifier: Framework :: Odoo :: 14.0
Classifier: License :: OSI Approved :: GNU Affero General Public License v3
Requires-Python: >=3.6
Requires-Dist: odoo14-addon-account-statement-import
Requires-Dist: odoo14-addon-edi-storage-oca
Requires-Dist: odoo14-addon-storage-backend-sftp
Requires-Dist: odoo<14.1dev,>=14.0a
